ckan_datapackage_tools/VERSION
ckan_datapackage_tools/__init__.py
ckan_datapackage_tools/converter.py
ckan_datapackage_tools-0.1.0.dist-info/LICENSE.md
ckan_datapackage_tools-0.1.0.dist-info/METADATA
ckan_datapackage_tools-0.1.0.dist-info/WHEEL
ckan_datapackage_tools-0.1.0.dist-info/top_level.txt
ckan_datapackage_tools-0.1.0.dist-info/RECORD
