Metadata-Version: 2.1
Name: ckan-datapackage-tools
Version: 0.1.0
Summary: {{ DESCRIPTION }}
Home-page: https://github.com/frictionlessdata/ckan_datapackage_tools
Author: Open Knowledge International
License: MIT
Keywords: data,ckan
Platform: UNKNOWN
Classifier: Environment :: Web Environment
Classifier: Intended Audience :: Developers
Classifier: License :: OSI Approved :: MIT License
Classifier: Operating System :: OS Independent
Classifier: Programming Language :: Python :: 3.6
Classifier: Programming Language :: Python :: 2.7
Classifier: Topic :: Internet :: WWW/HTTP :: Dynamic Content
Classifier: Topic :: Software Development :: Libraries :: Python Modules
Requires-Dist: six (<2.0,>=1.9)
Requires-Dist: python-slugify (<2.0,>=1.0)
Provides-Extra: develop
Requires-Dist: pylama ; extra == 'develop'
Requires-Dist: tox ; extra == 'develop'
Requires-Dist: requests-mock ; extra == 'develop'
